py_secure_shell_automator/__init__.py
py_secure_shell_automator/base_ssh/__init__.py
py_secure_shell_automator/base_ssh/base_ssh.py
py_secure_shell_automator/base_ssh/exceptions.py
py_secure_shell_automator/files_operations/__init__.py
py_secure_shell_automator/files_operations/exceptions.py
py_secure_shell_automator/files_operations/files_operations.py
py_secure_shell_automator/get_system_info/__init__.py
py_secure_shell_automator/get_system_info/exceptions.py
py_secure_shell_automator/get_system_info/get_system_info.py
py_secure_shell_automator/models/__init__.py
py_secure_shell_automator/models/executions_results.py
py_secure_shell_automator/processes_operations/__init__.py
py_secure_shell_automator/processes_operations/exceptions.py
py_secure_shell_automator/processes_operations/processes_operations.py
py_secure_shell_automator/py_secure_shell_automator.py
py_secure_shell_automator/user_operations/__init__.py
py_secure_shell_automator/user_operations/exceptions.py
py_secure_shell_automator/user_operations/user_operations.py
py_secure_shell_automator-0.1.7.dist-info/LICENSE
py_secure_shell_automator-0.1.7.dist-info/METADATA
py_secure_shell_automator-0.1.7.dist-info/WHEEL
py_secure_shell_automator-0.1.7.dist-info/entry_points.txt
py_secure_shell_automator-0.1.7.dist-info/RECORD
