Metadata-Version: 2.3
Name: py_secure_shell_automator
Version: 0.1.7
Summary: A Comprehensive SSH Management Library in Python
License: MIT
Author: Antonio Costa
Author-email: antonio.costa.dev@gmail.com
Requires-Python: >=3.10,<4.0
Classifier: License :: OSI Approved :: MIT License
Classifier: Programming Language :: Python :: 3
Classifier: Programming Language :: Python :: 3.10
Classifier: Programming Language :: Python :: 3.11
Classifier: Programming Language :: Python :: 3.12
Classifier: Programming Language :: Python :: 3.13
Requires-Dist: paramiko (>=3.4.0,<4.0.0)
Project-URL: Homepage, https://github.com/AntonioJCosta/py_secure_shell_automator
Project-URL: Repository, https://github.com/AntonioJCosta/py_secure_shell_automator
